datacenter_leo.py
setup.py
leodatacenter_package.egg-info/PKG-INFO
leodatacenter_package.egg-info/SOURCES.txt
leodatacenter_package.egg-info/dependency_links.txt
leodatacenter_package.egg-info/requires.txt
leodatacenter_package.egg-info/top_level.txt